fast_task_api/CONSTS.py
fast_task_api/__init__.py
fast_task_api/fast_task_api.py
fast_task_api/settings.py
fast_task_api/compatibility/HealthCheck.py
fast_task_api/compatibility/LimitedUploadFile.py
fast_task_api/compatibility/__init__.py
fast_task_api/compatibility/upload.py
fast_task_api/core/__init__.py
fast_task_api/core/job_store.py
fast_task_api/core/utils.py
fast_task_api/core/job/__init__.py
fast_task_api/core/job/base_job.py
fast_task_api/core/job/job_progress.py
fast_task_api/core/job/job_result.py
fast_task_api/core/routers/__init__.py
fast_task_api/core/routers/_exceptions.py
fast_task_api/core/routers/_fastapi_router.py
fast_task_api/core/routers/_runpod_router.py
fast_task_api/core/routers/_socaity_router.py
fast_task_api/core/routers/router_mixins/__init__.py
fast_task_api/core/routers/router_mixins/_base_file_handling_mixin.py
fast_task_api/core/routers/router_mixins/_fast_api_exception_handling.py
fast_task_api/core/routers/router_mixins/_fast_api_file_handling_mixin.py
fast_task_api/core/routers/router_mixins/_queue_mixin.py
fast_task_api/core/routers/router_mixins/job_queue.py
fast_task_api-1.3.2.dist-info/licenses/LICENSE
fast_task_api-1.3.2.dist-info/METADATA
fast_task_api-1.3.2.dist-info/WHEEL
fast_task_api-1.3.2.dist-info/top_level.txt
fast_task_api-1.3.2.dist-info/RECORD
