Metadata-Version: 2.4
Name: fast-task-api
Version: 1.3.2
Summary: Create web-APIs for long-running tasks
Author: SocAIty
License:                     GNU GENERAL PUBLIC LICENSE
Project-URL: Repository, https://github.com/SocAIty/fast-task-api
Project-URL: Homepage, https://www.socaity.ai
Requires-Python: >=3.8
License-File: LICENSE
Requires-Dist: uvicorn
Requires-Dist: fastapi
Requires-Dist: python-multipart>=0.0.20
Requires-Dist: media-toolkit>=0.02.21
Provides-Extra: runpod
Requires-Dist: runpod>=1.7.7; extra == "runpod"
Dynamic: license-file
